LICENSE
README.md
setup.cfg
setup.py
smsman/__init__.py
smsman/errors.py
smsman/smsman.py
smsman.egg-info/PKG-INFO
smsman.egg-info/SOURCES.txt
smsman.egg-info/dependency_links.txt
smsman.egg-info/requires.txt
smsman.egg-info/top_level.txt