Metadata-Version: 2.1
Name: smsman
Version: 1.0.1
Summary: A package to simplify work with the sms-man API
Home-page: https://github.com/smsmancom/smsman/
Author: Dmitry Tikhomirov
Author-email: dimasta00@gmail.com
License: UNKNOWN
Platform: UNKNOWN
Classifier: License :: OSI Approved :: GNU General Public License v3 (GPLv3)
Classifier: Programming Language :: Python :: 3.6
Classifier: Programming Language :: Python :: 3.7
Classifier: Programming Language :: Python :: 3.8
Classifier: Programming Language :: Python :: 3.9
License-File: LICENSE
